dev_project/__init__.py
dev_project/asgi.py
dev_project/settings.py
dev_project/urls.py
dev_project/wsgi.py
shared_service/__init__.py
shared_service/migrations/__init__.py
shared_service/shared_service/__init__.py
shared_service/shared_service/admin.py
shared_service/shared_service/apps.py
shared_service/shared_service/models.py
shared_service/shared_service/service.py
shared_service/shared_service/tests.py
shared_service/shared_service/views.py
shared_service-0.1.0.dist-info/METADATA
shared_service-0.1.0.dist-info/WHEEL
shared_service-0.1.0.dist-info/top_level.txt
shared_service-0.1.0.dist-info/RECORD
