Metadata-Version: 2.4
Name: shared-service
Version: 0.1.0
Summary: A reusable Django shared service
Home-page: https://github.com/yourusername/shared-service
Author: Your Name
Author-email: your@email.com
Classifier: Framework :: Django
Classifier: Programming Language :: Python :: 3
Requires-Dist: Django>=3.2
Dynamic: author
Dynamic: author-email
Dynamic: classifier
Dynamic: home-page
Dynamic: requires-dist
Dynamic: summary
